LICENSE
MANIFEST.in
README.rst
setup.cfg
setup.py
certbot_dns_he_ddns/__init__.py
certbot_dns_he_ddns/dns_he_ddns.py
certbot_dns_he_ddns.egg-info/PKG-INFO
certbot_dns_he_ddns.egg-info/SOURCES.txt
certbot_dns_he_ddns.egg-info/dependency_links.txt
certbot_dns_he_ddns.egg-info/entry_points.txt
certbot_dns_he_ddns.egg-info/requires.txt
certbot_dns_he_ddns.egg-info/top_level.txt