Metadata-Version: 2.1
Name: certbot-dns-he-ddns
Version: 0.1.0
Summary: Hurricane Electric dynamic DNS Authenticator plugin for Certbot
Home-page: https://github.com/mafredri/certbot-dns-he-ddns
Author: Mathias Fredriksson
Author-email: mafredri@gmail.com
License: MIT
Keywords: certbot dns hurricane-electric dns-01
Classifier: Environment :: Plugins
Classifier: Intended Audience :: System Administrators
Classifier: License :: OSI Approved :: MIT License
Classifier: Operating System :: POSIX :: Linux
Classifier: Programming Language :: Python
Classifier: Programming Language :: Python :: 2
Classifier: Programming Language :: Python :: 2.7
Classifier: Programming Language :: Python :: 3
Classifier: Programming Language :: Python :: 3.4
Classifier: Programming Language :: Python :: 3.5
Classifier: Programming Language :: Python :: 3.6
Classifier: Programming Language :: Python :: 3.7
Classifier: Topic :: Internet :: WWW/HTTP
Classifier: Topic :: Security
Classifier: Topic :: System :: Installation/Setup
Classifier: Topic :: System :: Networking
Classifier: Topic :: System :: Systems Administration
Classifier: Topic :: Utilities
Requires-Python: >=2.7, !=3.0.*, !=3.1.*, !=3.2.*, !=3.3.*
License-File: LICENSE
Requires-Dist: acme>=0.29.0
Requires-Dist: certbot>=0.34.0
Requires-Dist: requests
Requires-Dist: setuptools
Requires-Dist: zope.interface
